corsair_scan/__init__.py
corsair_scan/corsair_cli.py
corsair_scan/corsair_scan.py
corsair_scan-0.2.0.dist-info/LICENSE
corsair_scan-0.2.0.dist-info/METADATA
corsair_scan-0.2.0.dist-info/WHEEL
corsair_scan-0.2.0.dist-info/entry_points.txt
corsair_scan-0.2.0.dist-info/top_level.txt
corsair_scan-0.2.0.dist-info/RECORD
