Metadata-Version: 2.1
Name: corsair-scan
Version: 0.2.0
Summary: CORS testing library
Home-page: https://github.com/santandersecurityresearch/corsair_scan
Author: Santander UK Security Engineering
License: UNKNOWN
Keywords: corsair_scan
Platform: UNKNOWN
Classifier: Development Status :: 5 - Production/Stable
Classifier: Intended Audience :: Developers
Classifier: Natural Language :: English
Classifier: Programming Language :: Python :: 3.8
Classifier: Environment :: Console
Classifier: Topic :: Security
Requires-Dist: validators (>=0.14.3)
Requires-Dist: requests (>=2.23.0)
Requires-Dist: urllib3 (>=1.26.4)
Requires-Dist: tldextract (>=2.2.3)
Requires-Dist: click (>=7.1.2)
